pytest_docs/__init__.py
pytest_docs/element.py
pytest_docs/formatter.py
pytest_docs/plugin.py
pytest_docs/utils.py
pytest_docs/formatters/__init__.py
pytest_docs/formatters/markdown.py
pytest_docs/formatters/restuctured.py
pytest_docs-0.1.0.dist-info/LICENSE
pytest_docs-0.1.0.dist-info/METADATA
pytest_docs-0.1.0.dist-info/WHEEL
pytest_docs-0.1.0.dist-info/entry_points.txt
pytest_docs-0.1.0.dist-info/top_level.txt
pytest_docs-0.1.0.dist-info/RECORD
