Metadata-Version: 1.2
Name: pytest-docs
Version: 0.1.0
Summary: Documentation tool for pytest
Home-page: https://github.com/liiight/pytest-docs
Author: Or Carmi
Author-email: or.carmi82@gmail.com
Maintainer: Or Carmi
Maintainer-email: or.carmi82@gmail.com
License: MIT
Platform: UNKNOWN
Classifier: Development Status :: 4 - Beta
Classifier: Framework :: Pytest
Classifier: Intended Audience :: Developers
Classifier: Topic :: Software Development :: Testing
Classifier: Programming Language :: Python
Classifier: Programming Language :: Python :: 3
Classifier: Programming Language :: Python :: 3.4
Classifier: Programming Language :: Python :: 3.5
Classifier: Programming Language :: Python :: 3.6
Classifier: Programming Language :: Python :: 3.7
Classifier: Programming Language :: Python :: Implementation :: CPython
Classifier: Operating System :: OS Independent
Classifier: License :: OSI Approved :: MIT License
Requires-Python: >=3.4
